Workbook

Sheet Catalog
A1: L&M MEDICAL SOLUTIONS
A2: Orthopedic Catalog & Pricing
A3: Merged from the handwritten sheets • Currency: USD (per note on source pages)
A5: Item Code | B5: Category | C5: Item Name | D5: Variant / Size | E5: Notes | F5: Stock Qty | G5: U.P (USD) | H5: Sale Price (USD) | I5: Stock Cost Value | J5: Stock Sale Value | K5: Add to Order
A6: CS35-L14 | B6: Screws | C6: 3.5 Cortex Screw | D6: L14 | F6: 100 | G6: 4000 | H6: 13000 | I6: =F5*G5 -> #VALUE! | J6: =F5*H5 -> #VALUE!
A7: CS35-L16 | B7: Screws | C7: 3.5 Cortex Screw | D7: L16 | F7: 100 | G7: 4000 | H7: 13000 | I7: =F6*G6 -> 400000 | J7: =F6*H6 -> 1300000 | K7: Yes
A8: CS35-L18 | B8: Screws | C8: 3.5 Cortex Screw | D8: L18 | F8: 100 | G8: 4000 | H8: 13000 | I8: =F7*G7 -> 400000 | J8: =F7*H7 -> 1300000
A9: CS35-L20 | B9: Screws | C9: 3.5 Cortex Screw | D9: L20 | F9: 100 | G9: 4000 | H9: 13000 | I9: =F8*G8 -> 400000 | J9: =F8*H8 -> 1300000
A10: CS35-L22 | B10: Screws | C10: 3.5 Cortex Screw | D10: L22 | F10: 100 | G10: 4000 | H10: 13000 | I10: =F9*G9 -> 400000 | J10: =F9*H9 -> 1300000 | K10: No
A11: CS35-L24 | B11: Screws | C11: 3.5 Cortex Screw | D11: L24 | F11: 50 | G11: 4000 | H11: 13000 | I11: =F10*G10 -> 400000 | J11: =F10*H10 -> 1300000
A12: CS45-L20 | B12: Screws | C12: 4.5 Cortex Screw | D12: L20 | F12: 30 | G12: 4000 | H12: 15000 | I12: =F11*G11 -> 200000 | J12: =F11*H11 -> 650000 | K12: Yes
A13: CS45-L22 | B13: Screws | C13: 4.5 Cortex Screw | D13: L22 | F13: 30 | G13: 4000 | H13: 15000 | I13: =F12*G12 -> 120000 | J13: =F12*H12 -> 450000
A14: CS45-L24 | B14: Screws | C14: 4.5 Cortex Screw | D14: L24 | F14: 50 | G14: 4000 | H14: 15000 | I14: =F13*G13 -> 120000 | J14: =F13*H13 -> 450000
A15: CS45-L26 | B15: Screws | C15: 4.5 Cortex Screw | D15: L26 | F15: 50 | G15: 4000 | H15: 15000 | I15: =F14*G14 -> 200000 | J15: =F14*H14 -> 750000
A16: CS45-L30 | B16: Screws | C16: 4.5 Cortex Screw | D16: L30 | F16: 100 | G16: 4000 | H16: 15000 | I16: =F15*G15 -> 200000 | J16: =F15*H15 -> 750000
A17: CS45-L32 | B17: Screws | C17: 4.5 Cortex Screw | D17: L32 | F17: 100 | G17: 4000 | H17: 15000 | I17: =F16*G16 -> 400000 | J17: =F16*H16 -> 1500000 | K17: No
A18: CS45-L34 | B18: Screws | C18: 4.5 Cortex Screw | D18: L34 | F18: 100 | G18: 4000 | H18: 15000 | I18: =F17*G17 -> 400000 | J18: =F17*H17 -> 1500000
A19: CS45-L36 | B19: Screws | C19: 4.5 Cortex Screw | D19: L36 | F19: 100 | G19: 4000 | H19: 15000 | I19: =F18*G18 -> 400000 | J19: =F18*H18 -> 1500000
A20: CS45-L38 | B20: Screws | C20: 4.5 Cortex Screw | D20: L38 | F20: 100 | G20: 4000 | H20: 15000 | I20: =F19*G19 -> 400000 | J20: =F19*H19 -> 1500000
A21: CS45-L40 | B21: Screws | C21: 4.5 Cortex Screw | D21: L40 | F21: 100 | G21: 4000 | H21: 15000 | I21: =F20*G20 -> 400000 | J21: =F20*H20 -> 1500000
A22: CS45-L42 | B22: Screws | C22: 4.5 Cortex Screw | D22: L42 | F22: 100 | G22: 4000 | H22: 15000 | I22: =F21*G21 -> 400000 | J22: =F21*H21 -> 1500000
A23: DCP35-5H | B23: Plates | C23: 3.5 DCP Plate | D23: 5 holes | F23: 10 | G23: 20000 | H23: 80000 | I23: =F22*G22 -> 400000 | J23: =F22*H22 -> 1500000
A24: DCP35-6H | B24: Plates | C24: 3.5 DCP Plate | D24: 6 holes | F24: 15 | G24: 20000 | H24: 80000 | I24: =F23*G23 -> 200000 | J24: =F23*H23 -> 800000 | K24: Yes
A25: DCP35-7H | B25: Plates | C25: 3.5 DCP Plate | D25: 7 holes | F25: 15 | G25: 20000 | H25: 80000 | I25: =F24*G24 -> 300000 | J25: =F24*H24 -> 1200000
A26: DCP35-8H | B26: Plates | C26: 3.5 DCP Plate | D26: 8 holes | F26: 10 | G26: 20000 | H26: 80000 | I26: =F25*G25 -> 300000 | J26: =F25*H25 -> 1200000
A27: DCP45B-7H | B27: Plates | C27: 4.5 DCP Broad Plate | D27: 7 holes | F27: 5 | G27: 30000 | H27: 95000 | I27: =F26*G26 -> 200000 | J27: =F26*H26 -> 800000
A28: DCP45B-8H | B28: Plates | C28: 4.5 DCP Broad Plate | D28: 8 holes | F28: 10 | G28: 30000 | H28: 95000 | I28: =F27*G27 -> 150000 | J28: =F27*H27 -> 475000
A29: DCP45B-9H | B29: Plates | C29: 4.5 DCP Broad Plate | D29: 9 holes | F29: 10 | G29: 30000 | H29: 95000 | I29: =F28*G28 -> 300000 | J29: =F28*H28 -> 950000
A30: DCP45B-10H | B30: Plates | C30: 4.5 DCP Broad Plate | D30: 10 holes | F30: 10 | G30: 30000 | H30: 95000 | I30: =F29*G29 -> 300000 | J30: =F29*H29 -> 950000
A31: DCP45N-7H | B31: Plates | C31: 4.5 DCP Narrow Plate | D31: 7 holes | F31: 5 | G31: 30000 | H31: 95000 | I31: =F30*G30 -> 300000 | J31: =F30*H30 -> 950000
A32: DCP45N-8H | B32: Plates | C32: 4.5 DCP Narrow Plate | D32: 8 holes | F32: 10 | G32: 30000 | H32: 95000 | I32: =F31*G31 -> 150000 | J32: =F31*H31 -> 475000
A33: DCP45N-9H | B33: Plates | C33: 4.5 DCP Narrow Plate | D33: 9 holes | F33: 10 | G33: 30000 | H33: 95000 | I33: =F32*G32 -> 300000 | J33: =F32*H32 -> 950000
A34: DCP45N-10H | B34: Plates | C34: 4.5 DCP Narrow Plate | D34: 10 holes | F34: 10 | G34: 30000 | H34: 95000 | I34: =F33*G33 -> 300000 | J34: =F33*H33 -> 950000
A35: DCP45N-11H | B35: Plates | C35: 4.5 DCP Narrow Plate | D35: 11 holes | F35: 10 | G35: 30000 | H35: 95000 | I35: =F34*G34 -> 300000 | J35: =F34*H34 -> 950000
A36: DCP45N-12H | B36: Plates | C36: 4.5 DCP Narrow Plate | D36: 12 holes | F36: 10 | G36: 30000 | H36: 95000 | I36: =F35*G35 -> 300000 | J36: =F35*H35 -> 950000
... A38: EXT-M | B38: External Fixator | C38: External Fixator | D38: Medium | F38: 20 | G38: 75000 | H38: 350000 | I38: =F37*G37 -> 1500000 | J38: =F37*H37 -> 7000000
A39: EXT-S | B39: External Fixator | C39: External Fixator | D39: Small | F39: 25 | G39: 75000 | H39: 350000 | I39: =F38*G38 -> 1500000 | J39: =F38*H38 -> 7000000 | K39: Yes
A40: KW-1.2 | B40: Wires | C40: K-Wire | D40: 1.2 mm | F40: 100 | G40: 1200 | H40: 18000 | I40: =F39*G39 -> 1875000 | J40: =F39*H39 -> 8750000 | K40: Yes
A41: KW-1.5 | B41: Wires | C41: K-Wire | D41: 1.5 mm | F41: 100 | G41: 1200 | H41: 18000 | I41: =F40*G40 -> 120000 | J41: =F40*H40 -> 1800000 | K41: Yes
A42: KW-1.7 | B42: Wires | C42: K-Wire | D42: 1.7 mm | F42: 100 | G42: 1200 | H42: 18000 | I42: =F41*G41 -> 120000 | J42: =F41*H41 -> 1800000 | K42: Yes
A43: KW-2.0 | B43: Wires | C43: K-Wire | D43: 2.0 mm | F43: 100 | G43: 1200 | H43: 18000 | I43: =F42*G42 -> 120000 | J43: =F42*H42 -> 1800000
A44: CER-1 | B44: Wires | C44: Cerclage Wire | F44: 40 | G44: 3000 | H44: 20000 | I44: =F43*G43 -> 120000 | J44: =F43*H43 -> 1800000
A45: TEN-1.5 | B45: Nails | C45: Titanium Elastic Nail | D45: 1.5 mm | F45: 100 | G45: 15000 | H45: 50000 | I45: =F44*G44 -> 120000 | J45: =F44*H44 -> 800000 | K45: Yes
A46: TEN-2.0 | B46: Nails | C46: Titanium Elastic Nail | D46: 2.0 mm | F46: 100 | G46: 15000 | H46: 50000 | I46: =F45*G45 -> 1500000 | J46: =F45*H45 -> 5000000 | K46: Yes
A47: TEN-2.5 | B47: Nails | C47: Titanium Elastic Nail | D47: 2.5 mm | F47: 100 | G47: 15000 | H47: 50000 | I47: =F46*G46 -> 1500000 | J47: =F46*H46 -> 5000000 | K47: Yes
A48: TEN-3.0 | B48: Nails | C48: Titanium Elastic Nail | D48: 3.0 mm | F48: 100 | G48: 15000 | H48: 50000 | I48: =F47*G47 -> 1500000 | J48: =F47*H47 -> 5000000 | K48: Yes
A49: TEN-3.5 | B49: Nails | C49: Titanium Elastic Nail | D49: 3.5 mm | F49: 50 | G49: 15000 | H49: 50000 | I49: =F48*G48 -> 1500000 | J49: =F48*H48 -> 5000000 | K49: Yes
A50: SCH-3.0 | B50: Schanz Screws | C50: Schanz Screw | D50: 3.0 mm | F50: 50 | G50: 7000 | H50: 30000 | I50: =F49*G49 -> 750000 | J50: =F49*H49 -> 2500000
A51: SCH-3.5 | B51: Schanz Screws | C51: Schanz Screw | D51: 3.5 mm | F51: 50 | G51: 7000 | H51: 30000 | I51: =F50*G50 -> 350000 | J51: =F50*H50 -> 1500000
A52: SCH-4.0 | B52: Schanz Screws | C52: Schanz Screw | D52: 4.0 mm | F52: 50 | G52: 7000 | H52: 30000 | I52: =F51*G51 -> 350000 | J52: =F51*H51 -> 1500000
A53: SCH-4.5 | B53: Schanz Screws | C53: Schanz Screw | D53: 4.5 mm | F53: 50 | G53: 7000 | H53: 30000 | I53: =F52*G52 -> 350000 | J53: =F52*H52 -> 1500000
A54: CCS40-L16 | B54: Cancellous Screws | C54: 4.0 Cancellous Screw | D54: L16 | E54: Each length 20 pieces | F54: 20 | G54: 6000 | H54: 25000 | I54: =F53*G53 -> 350000 | J54: =F53*H53 -> 1500000 | K54: Yes
A55: CCS40-L18 | B55: Cancellous Screws | C55: 4.0 Cancellous Screw | D55: L18 | E55: Each length 20 pieces | F55: 20 | G55: 6000 | H55: 25000 | I55: =F54*G54 -> 120000 | J55: =F54*H54 -> 500000
A56: CCS40-L20 | B56: Cancellous Screws | C56: 4.0 Cancellous Screw | D56: L20 | E56: Each length 20 pieces | F56: 20 | G56: 6000 | H56: 25000 | I56: =F55*G55 -> 120000 | J56: =F55*H55 -> 500000
A57: CCS40-L22 | B57: Cancellous Screws | C57: 4.0 Cancellous Screw | D57: L22 | E57: Each length 20 pieces | F57: 20 | G57: 6000 | H57: 25000 | I57: =F56*G56 -> 120000 | J57: =F56*H56 -> 500000
A58: CCS40-L24 | B58: Cancellous Screws | C58: 4.0 Cancellous Screw | D58: L24 | E58: Each length 20 pieces | F58: 20 | G58: 6000 | H58: 25000 | I58: =F57*G57 -> 120000 | J58: =F57*H57 -> 500000
A59: CCS40-L26 | B59: Cancellous Screws | C59: 4.0 Cancellous Screw | D59: L26 | E59: Each length 20 pieces | F59: 20 | G59: 6000 | H59: 25000 | I59: =F58*G58 -> 120000 | J59: =F58*H58 -> 500000
A60: CCS40-L28 | B60: Cancellous Screws | C60: 4.0 Cancellous Screw | D60: L28 | E60: Each length 20 pieces | F60: 20 | G60: 6000 | H60: 25000 | I60: =F59*G59 -> 120000 | J60: =F59*H59 -> 500000
A61: CCS40-L30 | B61: Cancellous Screws | C61: 4.0 Cancellous Screw | D61: L30 | E61: Each length 20 pieces | F61: 20 | G61: 6000 | H61: 25000 | I61: =F60*G60 -> 120000 | J61: =F60*H60 -> 500000
A62: DHS-5H | B62: Plates | C62: DHS Plate | D62: 5 holes | F62: 10 | G62: 40000 | H62: 120000 | I62: =F61*G61 -> 120000 | J62: =F61*H61 -> 500000
A63: DHS-4H | B63: Plates | C63: DHS Plate | D63: 4 holes | F63: 20 | G63: 40000 | H63: 120000 | I63: =F62*G62 -> 400000 | J63: =F62*H62 -> 1200000
A64: LAG-L80 | B64: Screws | C64: Lag Screw | D64: L80 | E64: Each length 10 pieces | F64: 10 | G64: 20000 | H64: 45000 | I64: =F63*G63 -> 800000 | J64: =F63*H63 -> 2400000
A65: LAG-L85 | B65: Screws | C65: Lag Screw | D65: L85 | E65: Each length 10 pieces | F65: 10 | G65: 20000 | H65: 45000 | I65: =F64*G64 -> 200000 | J65: =F64*H64 -> 450000
A66: LAG-L90 | B66: Screws | C66: Lag Screw | D66: L90 | E66: Each length 10 pieces | F66: 10 | G66: 20000 | H66: 45000 | I66: =F65*G65 -> 200000 | J66: =F65*H65 -> 450000 | K66: No
A67: LAG-L95 | B67: Screws | C67: Lag Screw | D67: L95 | E67: Each length 10 pieces | F67: 10 | G67: 20000 | H67: 45000 | I67: =F66*G66 -> 200000 | J67: =F66*H66 -> 450000
A68: LAG-L100 | B68: Screws | C68: Lag Screw | D68: L100 | E68: Each length 10 pieces | F68: 10 | G68: 20000 | H68: 45000 | I68: =F67*G67 -> 200000 | J68: =F67*H67 -> 450000
A69: CAN40-L16 | B69: Cannulated Screws | C69: 4.0 Cannulated Screw | D69: L16 | E69: Each length 10 pieces | F69: 10 | G69: 15000 | H69: 40000 | I69: =F68*G68 -> 200000 | J69: =F68*H68 -> 450000
A70: CAN40-L18 | B70: Cannulated Screws | C70: 4.0 Cannulated Screw | D70: L18 | E70: Each length 10 pieces | F70: 10 | G70: 15000 | H70: 40000 | I70: =F69*G69 -> 150000 | J70: =F69*H69 -> 400000
A71: CAN40-L20 | B71: Cannulated Screws | C71: 4.0 Cannulated Screw | D71: L20 | E71: Each length 10 pieces | F71: 10 | G71: 15000 | H71: 40000 | I71: =F70*G70 -> 150000 | J71: =F70*H70 -> 400000
A72: CAN40-L22 | B72: Cannulated Screws | C72: 4.0 Cannulated Screw | D72: L22 | E72: Each length 10 pieces | F72: 10 | G72: 15000 | H72: 40000 | I72: =F71*G71 -> 150000 | J72: =F71*H71 -> 400000
A73: CAN40-L24 | B73: Cannulated Screws | C73: 4.0 Cannulated Screw | D73: L24 | E73: Each length 10 pieces | F73: 10 | G73: 15000 | H73: 40000 | I73: =F72*G72 -> 150000 | J73: =F72*H72 -> 400000
A74: CAN40-L26 | B74: Cannulated Screws | C74: 4.0 Cannulated Screw | D74: L26 | E74: Each length 10 pieces | F74: 10 | G74: 15000 | H74: 40000 | I74: =F73*G73 -> 150000 | J74: =F73*H73 -> 400000
A75: CAN40-L28 | B75: Cannulated Screws | C75: 4.0 Cannulated Screw | D75: L28 | E75: Each length 10 pieces | F75: 10 | G75: 15000 | H75: 40000 | I75: =F74*G74 -> 150000 | J75: =F74*H74 -> 400000
A76: CAN40-L30 | B76: Cannulated Screws | C76: 4.0 Cannulated Screw | D76: L30 | E76: Each length 10 pieces | F76: 10 | G76: 15000 | H76: 40000 | I76: =F75*G75 -> 150000 | J76: =F75*H75 -> 400000
A77: CAN40-L32 | B77: Cannulated Screws | C77: 4.0 Cannulated Screw | D77: L32 | E77: Each length 10 pieces | F77: 10 | G77: 15000 | H77: 40000 | I77: =F76*G76 -> 150000 | J77: =F76*H76 -> 400000
A78: CAN40-L34 | B78: Cannulated Screws | C78: 4.0 Cannulated Screw | D78: L34 | E78: Each length 10 pieces | F78: 10 | G78: 15000 | H78: 40000 | I78: =F77*G77 -> 150000 | J78: =F77*H77 -> 400000
... A86: CAN65-L60 | B86: Cannulated Screws | C86: 6.5 Cannulated Screw | D86: L60 | E86: Each length 10 pieces | F86: 10 | G86: 20000 | H86: 50000 | I86: =F85*G85 -> 200000 | J86: =F85*H85 -> 500000
A87: GAM-SET | B87: Gamma System | C87: Gamma Instrument Set | F87: 1 | G87: 1100 | H87: 3200 | I87: =F86*G86 -> 200000 | J87: =F86*H86 -> 500000
A88: GAM-NAIL-10 | B88: Gamma System | C88: Gamma Nail | D88: 10 mm | F88: 20 | G88: 25 | H88: 100 | I88: =F87*G87 -> 1100 | J88: =F87*H87 -> 3200
A89: GAM-NAIL-11 | B89: Gamma System | C89: Gamma Nail | D89: 11 mm | F89: 20 | G89: 25 | H89: 100 | I89: =F88*G88 -> 500 | J89: =F88*H88 -> 2000 | K89: Yes
A90: GAM-NAIL-12 | B90: Gamma System | C90: Gamma Nail | D90: 12 mm | F90: 10 | G90: 25 | H90: 100 | I90: =F89*G89 -> 500 | J90: =F89*H89 -> 2000 | K90: Yes
A91: GAM-LAG-L80 | B91: Gamma System | C91: Lag Screw for Gamma Nail | D91: L80 | E91: Each length 10 pieces | F91: 10 | G91: 12 | H91: 30 | I91: =F90*G90 -> 250 | J91: =F90*H90 -> 1000 | K91: Yes
A92: GAM-LAG-L85 | B92: Gamma System | C92: Lag Screw for Gamma Nail | D92: L85 | E92: Each length 10 pieces | F92: 10 | G92: 12 | H92: 30 | I92: =F91*G91 -> 120 | J92: =F91*H91 -> 300 | K92: Yes
A93: GAM-LAG-L90 | B93: Gamma System | C93: Lag Screw for Gamma Nail | D93: L90 | E93: Each length 10 pieces | F93: 10 | G93: 12 | H93: 30 | I93: =F92*G92 -> 120 | J93: =F92*H92 -> 300
A94: GAM-LAG-L95 | B94: Gamma System | C94: Lag Screw for Gamma Nail | D94: L95 | E94: Each length 10 pieces | F94: 10 | G94: 12 | H94: 30 | I94: =F93*G93 -> 120 | J94: =F93*H93 -> 300
A95: GAM-LAG-L100 | B95: Gamma System | C95: Lag Screw for Gamma Nail | D95: L100 | E95: Each length 10 pieces | F95: 10 | G95: 12 | H95: 30 | I95: =F94*G94 -> 120 | J95: =F94*H94 -> 300
A96: GAM-DLS-L26 | B96: Gamma System | C96: Distal Locking Screw for Gamma Nail | D96: L26 | E96: Each length 10 pieces | F96: 10 | G96: 5 | H96: 14 | I96: =F95*G95 -> 120 | J96: =F95*H95 -> 300
A97: GAM-DLS-L28 | B97: Gamma System | C97: Distal Locking Screw for Gamma Nail | D97: L28 | E97: Each length 10 pieces | F97: 10 | G97: 5 | H97: 14 | I97: =F96*G96 -> 50 | J97: =F96*H96 -> 140
A98: GAM-DLS-L30 | B98: Gamma System | C98: Distal Locking Screw for Gamma Nail | D98: L30 | E98: Each length 10 pieces | F98: 10 | G98: 5 | H98: 14 | I98: =F97*G97 -> 50 | J98: =F97*H97 -> 140
A99: GAM-DLS-L32 | B99: Gamma System | C99: Distal Locking Screw for Gamma Nail | D99: L32 | E99: Each length 10 pieces | F99: 10 | G99: 5 | H99: 14 | I99: =F98*G98 -> 50 | J99: =F98*H98 -> 140
A100: GAM-DLS-L34 | B100: Gamma System | C100: Distal Locking Screw for Gamma Nail | D100: L34 | E100: Each length 10 pieces | F100: 10 | G100: 5 | H100: 14 | I100: =F99*G99 -> 50 | J100: =F99*H99 -> 140
A101: GAM-DLS-L36 | B101: Gamma System | C101: Distal Locking Screw for Gamma Nail | D101: L36 | E101: Each length 10 pieces | F101: 10 | G101: 5 | H101: 14 | I101: =F100*G100 -> 50 | J101: =F100*H100 -> 140
A102: GAM-DLS-L38 | B102: Gamma System | C102: Distal Locking Screw for Gamma Nail | D102: L38 | E102: Each length 10 pieces | F102: 10 | G102: 5 | H102: 14 | I102: =F101*G101 -> 50 | J102: =F101*H101 -> 140
A103: GAM-DLS-L40 | B103: Gamma System | C103: Distal Locking Screw for Gamma Nail | D103: L40 | E103: Each length 10 pieces | F103: 10 | G103: 5 | H103: 14 | I103: =F102*G102 -> 50 | J103: =F102*H102 -> 140
A104: DFLP-L-5H | B104: Locked Plates | C104: Distal Femur Locked Plate | D104: Left / 5 holes | E104: 3 pieces each variant | F104: 3 | G104: 15 | H104: 70 | I104: =F103*G103 -> 50 | J104: =F103*H103 -> 140 | K104: Yes
A105: DFLP-L-7H | B105: Locked Plates | C105: Distal Femur Locked Plate | D105: Left / 7 holes | E105: 3 pieces each variant | F105: 3 | G105: 15 | H105: 70 | I105: =F104*G104 -> 45 | J105: =F104*H104 -> 210 | K105: Yes
A106: DFLP-L-9H | B106: Locked Plates | C106: Distal Femur Locked Plate | D106: Left / 9 holes | E106: 3 pieces each variant | F106: 3 | G106: 15 | H106: 70 | I106: =F105*G105 -> 45 | J106: =F105*H105 -> 210
A107: DFLP-L-11H | B107: Locked Plates | C107: Distal Femur Locked Plate | D107: Left / 11 holes | E107: 3 pieces each variant | F107: 3 | G107: 15 | H107: 70 | I107: =F106*G106 -> 45 | J107: =F106*H106 -> 210
A108: DFLP-R-5H | B108: Locked Plates | C108: Distal Femur Locked Plate | D108: Right / 5 holes | E108: 3 pieces each variant | F108: 3 | G108: 15 | H108: 70 | I108: =F107*G107 -> 45 | J108: =F107*H107 -> 210
A109: DFLP-R-7H | B109: Locked Plates | C109: Distal Femur Locked Plate | D109: Right / 7 holes | E109: 3 pieces each variant | F109: 3 | G109: 15 | H109: 70 | I109: =F108*G108 -> 45 | J109: =F108*H108 -> 210
...

Sheet Order
A1: L&M MEDICAL SOLUTIONS
A2: Order Sheet
A3: Choose an item code, enter order quantity, and totals will calculate automatically. | H3: Summary
H4: Total Cost | I4: =SUM(I7:I36) -> 60000
H5: Total Sales | I5: =SUM(J7:J36) -> 205000
A6: Line | B6: Item Code | C6: Item Name | D6: Variant / Size | E6: Available Qty | F6: Order Qty | G6: U.P (USD) | H6: Sale Price (USD) | I6: Total Cost | J6: Total Sales | K6: Margin
A7: =IF(B7="","",ROW()-6) -> 1 | B7: =IFERROR(INDEX(_xlfn._xlws.FILTER(Catalog!$A$6:$A$128,(Catalog!$K$6:$K$128="GENERATE ORDER")+(Catalog!$K$6:$K$128="Yes")),ROW()-6),"") -> CS35-L16 | C7: =IF($B7="","",_xlfn.XLOOKUP($B7,Catalog!$A$6:$A$128,Catalog!$C$6:$C$128,"")) -> 3.5 Cortex Screw | D7: =IF($B7="","",_xlfn.XLOOKUP($B7,Catalog!$A$6:$A$128,Catalog!$D$6:$D$128,"")) -> L16 | E7: 300 | F7: 10 | G7: =IF($B7="","",_xlfn.XLOOKUP($B7,Catalog!$A$6:$A$128,Catalog!$G$6:$G$128,"")) -> 4000 | H7: =IF($B7="","",_xlfn.XLOOKUP($B7,Catalog!$A$6:$A$128,Catalog!$H$6:$H$128,"")) -> 13000 | I7: =IF(OR($F7="",G7=""),"",$F7*G7) -> 40000 | J7: =IF(OR($F7="",H7=""),"",$F7*H7) -> 130000 | K7: =IF(OR(I7="",J7=""),"",J7-I7) -> 90000
A8: =IF(B8="","",ROW()-6) -> 2 | B8: =IFERROR(INDEX(_xlfn._xlws.FILTER(Catalog!$A$6:$A$128,(Catalog!$K$6:$K$128="GENERATE ORDER")+(Catalog!$K$6:$K$128="Yes")),ROW()-6),"") -> CS45-L20 | C8: =IF($B8="","",_xlfn.XLOOKUP($B8,Catalog!$A$6:$A$128,Catalog!$C$6:$C$128,"")) -> 4.5 Cortex Screw | D8: =IF($B8="","",_xlfn.XLOOKUP($B8,Catalog!$A$6:$A$128,Catalog!$D$6:$D$128,"")) -> L20 | E8: 200 | F8: 5 | G8: =IF($B8="","",_xlfn.XLOOKUP($B8,Catalog!$A$6:$A$128,Catalog!$G$6:$G$128,"")) -> 4000 | H8: =IF($B8="","",_xlfn.XLOOKUP($B8,Catalog!$A$6:$A$128,Catalog!$H$6:$H$128,"")) -> 15000 | I8: =IF(OR($F8="",G8=""),"",$F8*G8) -> 20000 | J8: =IF(OR($F8="",H8=""),"",$F8*H8) -> 75000 | K8: =IF(OR(I8="",J8=""),"",J8-I8) -> 55000
A9: =IF(B9="","",ROW()-6) -> 3 | B9: =IFERROR(INDEX(_xlfn._xlws.FILTER(Catalog!$A$6:$A$128,(Catalog!$K$6:$K$128="GENERATE ORDER")+(Catalog!$K$6:$K$128="Yes")),ROW()-6),"") -> DCP35-6H | C9: =IF($B9="","",_xlfn.XLOOKUP($B9,Catalog!$A$6:$A$128,Catalog!$C$6:$C$128,"")) -> 3.5 DCP Plate | D9: =IF($B9="","",_xlfn.XLOOKUP($B9,Catalog!$A$6:$A$128,Catalog!$D$6:$D$128,"")) -> 6 holes | E9: 50 | G9: =IF($B9="","",_xlfn.XLOOKUP($B9,Catalog!$A$6:$A$128,Catalog!$G$6:$G$128,"")) -> 20000 | H9: =IF($B9="","",_xlfn.XLOOKUP($B9,Catalog!$A$6:$A$128,Catalog!$H$6:$H$128,"")) -> 80000 | I9: =IF(OR($F9="",G9=""),"",$F9*G9) | J9: =IF(OR($F9="",H9=""),"",$F9*H9) | K9: =IF(OR(I9="",J9=""),"",J9-I9)
A10: =IF(B10="","",ROW()-6) -> 4 | B10: =IFERROR(INDEX(_xlfn._xlws.FILTER(Catalog!$A$6:$A$128,(Catalog!$K$6:$K$128="GENERATE ORDER")+(Catalog!$K$6:$K$128="Yes")),ROW()-6),"") -> EXT-S | C10: =IF($B10="","",_xlfn.XLOOKUP($B10,Catalog!$A$6:$A$128,Catalog!$C$6:$C$128,"")) -> External Fixator | D10: =IF($B10="","",_xlfn.XLOOKUP($B10,Catalog!$A$6:$A$128,Catalog!$D$6:$D$128,"")) -> Small | E10: 20 | G10: =IF($B10="","",_xlfn.XLOOKUP($B10,Catalog!$A$6:$A$128,Catalog!$G$6:$G$128,"")) -> 75000 | H10: =IF($B10="","",_xlfn.XLOOKUP($B10,Catalog!$A$6:$A$128,Catalog!$H$6:$H$128,"")) -> 350000 | I10: =IF(OR($F10="",G10=""),"",$F10*G10) | J10: =IF(OR($F10="",H10=""),"",$F10*H10) | K10: =IF(OR(I10="",J10=""),"",J10-I10)
A11: =IF(B11="","",ROW()-6) -> 5 | B11: =IFERROR(INDEX(_xlfn._xlws.FILTER(Catalog!$A$6:$A$128,(Catalog!$K$6:$K$128="GENERATE ORDER")+(Catalog!$K$6:$K$128="Yes")),ROW()-6),"") -> KW-1.2 | C11: =IF($B11="","",_xlfn.XLOOKUP($B11,Catalog!$A$6:$A$128,Catalog!$C$6:$C$128,"")) -> K-Wire | D11: =IF($B11="","",_xlfn.XLOOKUP($B11,Catalog!$A$6:$A$128,Catalog!$D$6:$D$128,"")) -> 1.2 mm | E11: 200 | G11: =IF($B11="","",_xlfn.XLOOKUP($B11,Catalog!$A$6:$A$128,Catalog!$G$6:$G$128,"")) -> 1200 | H11: =IF($B11="","",_xlfn.XLOOKUP($B11,Catalog!$A$6:$A$128,Catalog!$H$6:$H$128,"")) -> 18000 | I11: =IF(OR($F11="",G11=""),"",$F11*G11) | J11: =IF(OR($F11="",H11=""),"",$F11*H11) | K11: =IF(OR(I11="",J11=""),"",J11-I11)
A12: =IF(B12="","",ROW()-6) -> 6 | B12: =IFERROR(INDEX(_xlfn._xlws.FILTER(Catalog!$A$6:$A$128,(Catalog!$K$6:$K$128="GENERATE ORDER")+(Catalog!$K$6:$K$128="Yes")),ROW()-6),"") -> KW-1.5 | C12: =IF($B12="","",_xlfn.XLOOKUP($B12,Catalog!$A$6:$A$128,Catalog!$C$6:$C$128,"")) -> K-Wire | D12: =IF($B12="","",_xlfn.XLOOKUP($B12,Catalog!$A$6:$A$128,Catalog!$D$6:$D$128,"")) -> 1.5 mm | E12: 1 | G12: =IF($B12="","",_xlfn.XLOOKUP($B12,Catalog!$A$6:$A$128,Catalog!$G$6:$G$128,"")) -> 1200 | H12: =IF($B12="","",_xlfn.XLOOKUP($B12,Catalog!$A$6:$A$128,Catalog!$H$6:$H$128,"")) -> 18000 | I12: =IF(OR($F12="",G12=""),"",$F12*G12) | J12: =IF(OR($F12="",H12=""),"",$F12*H12) | K12: =IF(OR(I12="",J12=""),"",J12-I12)
A13: =IF(B13="","",ROW()-6) -> 7 | B13: =IFERROR(INDEX(_xlfn._xlws.FILTER(Catalog!$A$6:$A$128,(Catalog!$K$6:$K$128="GENERATE ORDER")+(Catalog!$K$6:$K$128="Yes")),ROW()-6),"") -> KW-1.7 | C13: =IF($B13="","",_xlfn.XLOOKUP($B13,Catalog!$A$6:$A$128,Catalog!$C$6:$C$128,"")) -> K-Wire | D13: =IF($B13="","",_xlfn.XLOOKUP($B13,Catalog!$A$6:$A$128,Catalog!$D$6:$D$128,"")) -> 1.7 mm | E13: 1 | G13: =IF($B13="","",_xlfn.XLOOKUP($B13,Catalog!$A$6:$A$128,Catalog!$G$6:$G$128,"")) -> 1200 | H13: =IF($B13="","",_xlfn.XLOOKUP($B13,Catalog!$A$6:$A$128,Catalog!$H$6:$H$128,"")) -> 18000 | I13: =IF(OR($F13="",G13=""),"",$F13*G13) | J13: =IF(OR($F13="",H13=""),"",$F13*H13) | K13: =IF(OR(I13="",J13=""),"",J13-I13)
A14: =IF(B14="","",ROW()-6) -> 8 | B14: =IFERROR(INDEX(_xlfn._xlws.FILTER(Catalog!$A$6:$A$128,(Catalog!$K$6:$K$128="GENERATE ORDER")+(Catalog!$K$6:$K$128="Yes")),ROW()-6),"") -> TEN-1.5 | C14: =IF($B14="","",_xlfn.XLOOKUP($B14,Catalog!$A$6:$A$128,Catalog!$C$6:$C$128,"")) -> Titanium Elastic Nail | D14: =IF($B14="","",_xlfn.XLOOKUP($B14,Catalog!$A$6:$A$128,Catalog!$D$6:$D$128,"")) -> 1.5 mm | E14: 30 | G14: =IF($B14="","",_xlfn.XLOOKUP($B14,Catalog!$A$6:$A$128,Catalog!$G$6:$G$128,"")) -> 15000 | H14: =IF($B14="","",_xlfn.XLOOKUP($B14,Catalog!$A$6:$A$128,Catalog!$H$6:$H$128,"")) -> 50000 | I14: =IF(OR($F14="",G14=""),"",$F14*G14) | J14: =IF(OR($F14="",H14=""),"",$F14*H14) | K14: =IF(OR(I14="",J14=""),"",J14-I14)
A15: =IF(B15="","",ROW()-6) -> 9 | B15: =IFERROR(INDEX(_xlfn._xlws.FILTER(Catalog!$A$6:$A$128,(Catalog!$K$6:$K$128="GENERATE ORDER")+(Catalog!$K$6:$K$128="Yes")),ROW()-6),"") -> TEN-2.0 | C15: =IF($B15="","",_xlfn.XLOOKUP($B15,Catalog!$A$6:$A$128,Catalog!$C$6:$C$128,"")) -> Titanium Elastic Nail | D15: =IF($B15="","",_xlfn.XLOOKUP($B15,Catalog!$A$6:$A$128,Catalog!$D$6:$D$128,"")) -> 2.0 mm | E15: 30 | G15: =IF($B15="","",_xlfn.XLOOKUP($B15,Catalog!$A$6:$A$128,Catalog!$G$6:$G$128,"")) -> 15000 | H15: =IF($B15="","",_xlfn.XLOOKUP($B15,Catalog!$A$6:$A$128,Catalog!$H$6:$H$128,"")) -> 50000 | I15: =IF(OR($F15="",G15=""),"",$F15*G15) | J15: =IF(OR($F15="",H15=""),"",$F15*H15) | K15: =IF(OR(I15="",J15=""),"",J15-I15)
A16: =IF(B16="","",ROW()-6) -> 10 | B16: =IFERROR(INDEX(_xlfn._xlws.FILTER(Catalog!$A$6:$A$128,(Catalog!$K$6:$K$128="GENERATE ORDER")+(Catalog!$K$6:$K$128="Yes")),ROW()-6),"") -> TEN-2.5 | C16: =IF($B16="","",_xlfn.XLOOKUP($B16,Catalog!$A$6:$A$128,Catalog!$C$6:$C$128,"")) -> Titanium Elastic Nail | D16: =IF($B16="","",_xlfn.XLOOKUP($B16,Catalog!$A$6:$A$128,Catalog!$D$6:$D$128,"")) -> 2.5 mm | E16: 30 | G16: =IF($B16="","",_xlfn.XLOOKUP($B16,Catalog!$A$6:$A$128,Catalog!$G$6:$G$128,"")) -> 15000 | H16: =IF($B16="","",_xlfn.XLOOKUP($B16,Catalog!$A$6:$A$128,Catalog!$H$6:$H$128,"")) -> 50000 | I16: =IF(OR($F16="",G16=""),"",$F16*G16) | J16: =IF(OR($F16="",H16=""),"",$F16*H16) | K16: =IF(OR(I16="",J16=""),"",J16-I16)
A17: =IF(B17="","",ROW()-6) -> 11 | B17: =IFERROR(INDEX(_xlfn._xlws.FILTER(Catalog!$A$6:$A$128,(Catalog!$K$6:$K$128="GENERATE ORDER")+(Catalog!$K$6:$K$128="Yes")),ROW()-6),"") -> TEN-3.0 | C17: =IF($B17="","",_xlfn.XLOOKUP($B17,Catalog!$A$6:$A$128,Catalog!$C$6:$C$128,"")) -> Titanium Elastic Nail | D17: =IF($B17="","",_xlfn.XLOOKUP($B17,Catalog!$A$6:$A$128,Catalog!$D$6:$D$128,"")) -> 3.0 mm | E17: 30 | G17: =IF($B17="","",_xlfn.XLOOKUP($B17,Catalog!$A$6:$A$128,Catalog!$G$6:$G$128,"")) -> 15000 | H17: =IF($B17="","",_xlfn.XLOOKUP($B17,Catalog!$A$6:$A$128,Catalog!$H$6:$H$128,"")) -> 50000 | I17: =IF(OR($F17="",G17=""),"",$F17*G17) | J17: =IF(OR($F17="",H17=""),"",$F17*H17) | K17: =IF(OR(I17="",J17=""),"",J17-I17)
A18: =IF(B18="","",ROW()-6) -> 12 | B18: =IFERROR(INDEX(_xlfn._xlws.FILTER(Catalog!$A$6:$A$128,(Catalog!$K$6:$K$128="GENERATE ORDER")+(Catalog!$K$6:$K$128="Yes")),ROW()-6),"") -> TEN-3.5 | C18: =IF($B18="","",_xlfn.XLOOKUP($B18,Catalog!$A$6:$A$128,Catalog!$C$6:$C$128,"")) -> Titanium Elastic Nail | D18: =IF($B18="","",_xlfn.XLOOKUP($B18,Catalog!$A$6:$A$128,Catalog!$D$6:$D$128,"")) -> 3.5 mm | E18: 30 | G18: =IF($B18="","",_xlfn.XLOOKUP($B18,Catalog!$A$6:$A$128,Catalog!$G$6:$G$128,"")) -> 15000 | H18: =IF($B18="","",_xlfn.XLOOKUP($B18,Catalog!$A$6:$A$128,Catalog!$H$6:$H$128,"")) -> 50000 | I18: =IF(OR($F18="",G18=""),"",$F18*G18) | J18: =IF(OR($F18="",H18=""),"",$F18*H18) | K18: =IF(OR(I18="",J18=""),"",J18-I18)
A19: =IF(B19="","",ROW()-6) -> 13 | B19: =IFERROR(INDEX(_xlfn._xlws.FILTER(Catalog!$A$6:$A$128,(Catalog!$K$6:$K$128="GENERATE ORDER")+(Catalog!$K$6:$K$128="Yes")),ROW()-6),"") -> CCS40-L16 | C19: =IF($B19="","",_xlfn.XLOOKUP($B19,Catalog!$A$6:$A$128,Catalog!$C$6:$C$128,"")) -> 4.0 Cancellous Screw | D19: =IF($B19="","",_xlfn.XLOOKUP($B19,Catalog!$A$6:$A$128,Catalog!$D$6:$D$128,"")) -> L16 | E19: 200 | G19: =IF($B19="","",_xlfn.XLOOKUP($B19,Catalog!$A$6:$A$128,Catalog!$G$6:$G$128,"")) -> 6000 | H19: =IF($B19="","",_xlfn.XLOOKUP($B19,Catalog!$A$6:$A$128,Catalog!$H$6:$H$128,"")) -> 25000 | I19: =IF(OR($F19="",G19=""),"",$F19*G19) | J19: =IF(OR($F19="",H19=""),"",$F19*H19) | K19: =IF(OR(I19="",J19=""),"",J19-I19)
A20: =IF(B20="","",ROW()-6) -> 14 | B20: =IFERROR(INDEX(_xlfn._xlws.FILTER(Catalog!$A$6:$A$128,(Catalog!$K$6:$K$128="GENERATE ORDER")+(Catalog!$K$6:$K$128="Yes")),ROW()-6),"") -> GAM-NAIL-11 | C20: =IF($B20="","",_xlfn.XLOOKUP($B20,Catalog!$A$6:$A$128,Catalog!$C$6:$C$128,"")) -> Gamma Nail | D20: =IF($B20="","",_xlfn.XLOOKUP($B20,Catalog!$A$6:$A$128,Catalog!$D$6:$D$128,"")) -> 11 mm | E20: 30 | G20: =IF($B20="","",_xlfn.XLOOKUP($B20,Catalog!$A$6:$A$128,Catalog!$G$6:$G$128,"")) -> 25 | H20: =IF($B20="","",_xlfn.XLOOKUP($B20,Catalog!$A$6:$A$128,Catalog!$H$6:$H$128,"")) -> 100 | I20: =IF(OR($F20="",G20=""),"",$F20*G20) | J20: =IF(OR($F20="",H20=""),"",$F20*H20) | K20: =IF(OR(I20="",J20=""),"",J20-I20)
... A24: =IF(B24="","",ROW()-6) -> 18 | B24: =IFERROR(INDEX(_xlfn._xlws.FILTER(Catalog!$A$6:$A$128,(Catalog!$K$6:$K$128="GENERATE ORDER")+(Catalog!$K$6:$K$128="Yes")),ROW()-6),"") -> DFLP-L-5H | C24: =IF($B24="","",_xlfn.XLOOKUP($B24,Catalog!$A$6:$A$128,Catalog!$C$6:$C$128,"")) -> Distal Femur Locked Plate | D24: =IF($B24="","",_xlfn.XLOOKUP($B24,Catalog!$A$6:$A$128,Catalog!$D$6:$D$128,"")) -> Left / 5 holes | E24: 24 | G24: =IF($B24="","",_xlfn.XLOOKUP($B24,Catalog!$A$6:$A$128,Catalog!$G$6:$G$128,"")) -> 15 | H24: =IF($B24="","",_xlfn.XLOOKUP($B24,Catalog!$A$6:$A$128,Catalog!$H$6:$H$128,"")) -> 70 | I24: =IF(OR($F24="",G24=""),"",$F24*G24) | J24: =IF(OR($F24="",H24=""),"",$F24*H24) | K24: =IF(OR(I24="",J24=""),"",J24-I24)
A25: =IF(B25="","",ROW()-6) -> 19 | B25: =IFERROR(INDEX(_xlfn._xlws.FILTER(Catalog!$A$6:$A$128,(Catalog!$K$6:$K$128="GENERATE ORDER")+(Catalog!$K$6:$K$128="Yes")),ROW()-6),"") -> DFLP-L-7H | C25: =IF($B25="","",_xlfn.XLOOKUP($B25,Catalog!$A$6:$A$128,Catalog!$C$6:$C$128,"")) -> Distal Femur Locked Plate | D25: =IF($B25="","",_xlfn.XLOOKUP($B25,Catalog!$A$6:$A$128,Catalog!$D$6:$D$128,"")) -> Left / 7 holes | E25: =IF($B25="","",_xlfn.XLOOKUP($B25,Catalog!$A$6:$A$128,Catalog!$F$6:$F$128,"")) -> 3 | G25: =IF($B25="","",_xlfn.XLOOKUP($B25,Catalog!$A$6:$A$128,Catalog!$G$6:$G$128,"")) -> 15 | H25: =IF($B25="","",_xlfn.XLOOKUP($B25,Catalog!$A$6:$A$128,Catalog!$H$6:$H$128,"")) -> 70 | I25: =IF(OR($F25="",G25=""),"",$F25*G25) | J25: =IF(OR($F25="",H25=""),"",$F25*H25) | K25: =IF(OR(I25="",J25=""),"",J25-I25)
A26: =IF(B26="","",ROW()-6) -> 20 | B26: =IFERROR(INDEX(_xlfn._xlws.FILTER(Catalog!$A$6:$A$128,(Catalog!$K$6:$K$128="GENERATE ORDER")+(Catalog!$K$6:$K$128="Yes")),ROW()-6),"") -> PHLP-3H | C26: =IF($B26="","",_xlfn.XLOOKUP($B26,Catalog!$A$6:$A$128,Catalog!$C$6:$C$128,"")) -> Proximal Humerus Locked Plate | D26: =IF($B26="","",_xlfn.XLOOKUP($B26,Catalog!$A$6:$A$128,Catalog!$D$6:$D$128,"")) -> 3 holes | E26: =IF($B26="","",_xlfn.XLOOKUP($B26,Catalog!$A$6:$A$128,Catalog!$F$6:$F$128,"")) -> 4 | G26: =IF($B26="","",_xlfn.XLOOKUP($B26,Catalog!$A$6:$A$128,Catalog!$G$6:$G$128,"")) -> 15 | H26: =IF($B26="","",_xlfn.XLOOKUP($B26,Catalog!$A$6:$A$128,Catalog!$H$6:$H$128,"")) -> 75 | I26: =IF(OR($F26="",G26=""),"",$F26*G26) | J26: =IF(OR($F26="",H26=""),"",$F26*H26) | K26: =IF(OR(I26="",J26=""),"",J26-I26)
A27: =IF(B27="","",ROW()-6) -> 21 | B27: =IFERROR(INDEX(_xlfn._xlws.FILTER(Catalog!$A$6:$A$128,(Catalog!$K$6:$K$128="GENERATE ORDER")+(Catalog!$K$6:$K$128="Yes")),ROW()-6),"") -> PHLP-4H | C27: =IF($B27="","",_xlfn.XLOOKUP($B27,Catalog!$A$6:$A$128,Catalog!$C$6:$C$128,"")) -> Proximal Humerus Locked Plate | D27: =IF($B27="","",_xlfn.XLOOKUP($B27,Catalog!$A$6:$A$128,Catalog!$D$6:$D$128,"")) -> 4 holes | E27: =IF($B27="","",_xlfn.XLOOKUP($B27,Catalog!$A$6:$A$128,Catalog!$F$6:$F$128,"")) -> 4 | G27: =IF($B27="","",_xlfn.XLOOKUP($B27,Catalog!$A$6:$A$128,Catalog!$G$6:$G$128,"")) -> 15 | H27: =IF($B27="","",_xlfn.XLOOKUP($B27,Catalog!$A$6:$A$128,Catalog!$H$6:$H$128,"")) -> 75 | I27: =IF(OR($F27="",G27=""),"",$F27*G27) | J27: =IF(OR($F27="",H27=""),"",$F27*H27) | K27: =IF(OR(I27="",J27=""),"",J27-I27)
A28: =IF(B28="","",ROW()-6) -> 22 | B28: =IFERROR(INDEX(_xlfn._xlws.FILTER(Catalog!$A$6:$A$128,(Catalog!$K$6:$K$128="GENERATE ORDER")+(Catalog!$K$6:$K$128="Yes")),ROW()-6),"") -> PHLP-5H | C28: =IF($B28="","",_xlfn.XLOOKUP($B28,Catalog!$A$6:$A$128,Catalog!$C$6:$C$128,"")) -> Proximal Humerus Locked Plate | D28: =IF($B28="","",_xlfn.XLOOKUP($B28,Catalog!$A$6:$A$128,Catalog!$D$6:$D$128,"")) -> 5 holes | E28: =IF($B28="","",_xlfn.XLOOKUP($B28,Catalog!$A$6:$A$128,Catalog!$F$6:$F$128,"")) -> 4 | G28: =IF($B28="","",_xlfn.XLOOKUP($B28,Catalog!$A$6:$A$128,Catalog!$G$6:$G$128,"")) -> 15 | H28: =IF($B28="","",_xlfn.XLOOKUP($B28,Catalog!$A$6:$A$128,Catalog!$H$6:$H$128,"")) -> 75 | I28: =IF(OR($F28="",G28=""),"",$F28*G28) | J28: =IF(OR($F28="",H28=""),"",$F28*H28) | K28: =IF(OR(I28="",J28=""),"",J28-I28)
A29: =IF(B29="","",ROW()-6) -> 23 | B29: =IFERROR(INDEX(_xlfn._xlws.FILTER(Catalog!$A$6:$A$128,(Catalog!$K$6:$K$128="GENERATE ORDER")+(Catalog!$K$6:$K$128="Yes")),ROW()-6),"") -> DTLP-L-6H | C29: =IF($B29="","",_xlfn.XLOOKUP($B29,Catalog!$A$6:$A$128,Catalog!$C$6:$C$128,"")) -> Distal Tibia Locked Plate | D29: =IF($B29="","",_xlfn.XLOOKUP($B29,Catalog!$A$6:$A$128,Catalog!$D$6:$D$128,"")) -> Left / 6 holes | E29: =IF($B29="","",_xlfn.XLOOKUP($B29,Catalog!$A$6:$A$128,Catalog!$F$6:$F$128,"")) -> 3 | G29: =IF($B29="","",_xlfn.XLOOKUP($B29,Catalog!$A$6:$A$128,Catalog!$G$6:$G$128,"")) -> 15 | H29: =IF($B29="","",_xlfn.XLOOKUP($B29,Catalog!$A$6:$A$128,Catalog!$H$6:$H$128,"")) -> 90 | I29: =IF(OR($F29="",G29=""),"",$F29*G29) | J29: =IF(OR($F29="",H29=""),"",$F29*H29) | K29: =IF(OR(I29="",J29=""),"",J29-I29)
A30: =IF(B30="","",ROW()-6) -> 24 | B30: =IFERROR(INDEX(_xlfn._xlws.FILTER(Catalog!$A$6:$A$128,(Catalog!$K$6:$K$128="GENERATE ORDER")+(Catalog!$K$6:$K$128="Yes")),ROW()-6),"") -> DTLP-L-7H | C30: =IF($B30="","",_xlfn.XLOOKUP($B30,Catalog!$A$6:$A$128,Catalog!$C$6:$C$128,"")) -> Distal Tibia Locked Plate | D30: =IF($B30="","",_xlfn.XLOOKUP($B30,Catalog!$A$6:$A$128,Catalog!$D$6:$D$128,"")) -> Left / 7 holes | E30: =IF($B30="","",_xlfn.XLOOKUP($B30,Catalog!$A$6:$A$128,Catalog!$F$6:$F$128,"")) -> 3 | G30: =IF($B30="","",_xlfn.XLOOKUP($B30,Catalog!$A$6:$A$128,Catalog!$G$6:$G$128,"")) -> 15 | H30: =IF($B30="","",_xlfn.XLOOKUP($B30,Catalog!$A$6:$A$128,Catalog!$H$6:$H$128,"")) -> 90 | I30: =IF(OR($F30="",G30=""),"",$F30*G30) | J30: =IF(OR($F30="",H30=""),"",$F30*H30) | K30: =IF(OR(I30="",J30=""),"",J30-I30)
A31: =IF(B31="","",ROW()-6) -> 25 | B31: =IFERROR(INDEX(_xlfn._xlws.FILTER(Catalog!$A$6:$A$128,(Catalog!$K$6:$K$128="GENERATE ORDER")+(Catalog!$K$6:$K$128="Yes")),ROW()-6),"") -> DTLP-L-8H | C31: =IF($B31="","",_xlfn.XLOOKUP($B31,Catalog!$A$6:$A$128,Catalog!$C$6:$C$128,"")) -> Distal Tibia Locked Plate | D31: =IF($B31="","",_xlfn.XLOOKUP($B31,Catalog!$A$6:$A$128,Catalog!$D$6:$D$128,"")) -> Left / 8 holes | E31: =IF($B31="","",_xlfn.XLOOKUP($B31,Catalog!$A$6:$A$128,Catalog!$F$6:$F$128,"")) -> 3 | G31: =IF($B31="","",_xlfn.XLOOKUP($B31,Catalog!$A$6:$A$128,Catalog!$G$6:$G$128,"")) -> 15 | H31: =IF($B31="","",_xlfn.XLOOKUP($B31,Catalog!$A$6:$A$128,Catalog!$H$6:$H$128,"")) -> 90 | I31: =IF(OR($F31="",G31=""),"",$F31*G31) | J31: =IF(OR($F31="",H31=""),"",$F31*H31) | K31: =IF(OR(I31="",J31=""),"",J31-I31)
A32: =IF(B32="","",ROW()-6) -> 26 | B32: =IFERROR(INDEX(_xlfn._xlws.FILTER(Catalog!$A$6:$A$128,(Catalog!$K$6:$K$128="GENERATE ORDER")+(Catalog!$K$6:$K$128="Yes")),ROW()-6),"") -> LOCK50-MIX | C32: =IF($B32="","",_xlfn.XLOOKUP($B32,Catalog!$A$6:$A$128,Catalog!$C$6:$C$128,"")) -> 5.0 Locked Screws for Locked Plates | D32: =IF($B32="","",_xlfn.XLOOKUP($B32,Catalog!$A$6:$A$128,Catalog!$D$6:$D$128,"")) -> L26-L75 mixed | E32: =IF($B32="","",_xlfn.XLOOKUP($B32,Catalog!$A$6:$A$128,Catalog!$F$6:$F$128,"")) -> 130 | G32: =IF($B32="","",_xlfn.XLOOKUP($B32,Catalog!$A$6:$A$128,Catalog!$G$6:$G$128,"")) -> 5 | H32: =IF($B32="","",_xlfn.XLOOKUP($B32,Catalog!$A$6:$A$128,Catalog!$H$6:$H$128,"")) -> 14 | I32: =IF(OR($F32="",G32=""),"",$F32*G32) | J32: =IF(OR($F32="",H32=""),"",$F32*H32) | K32: =IF(OR(I32="",J32=""),"",J32-I32)
A33: =IF(B33="","",ROW()-6) | B33: =IFERROR(INDEX(_xlfn._xlws.FILTER(Catalog!$A$6:$A$128,(Catalog!$K$6:$K$128="GENERATE ORDER")+(Catalog!$K$6:$K$128="Yes")),ROW()-6),"") | D33: =IF($B33="","",_xlfn.XLOOKUP($B33,Catalog!$A$6:$A$128,Catalog!$D$6:$D$128,"")) | E33: =IF($B33="","",_xlfn.XLOOKUP($B33,Catalog!$A$6:$A$128,Catalog!$F$6:$F$128,"")) | G33: =IF($B33="","",_xlfn.XLOOKUP($B33,Catalog!$A$6:$A$128,Catalog!$G$6:$G$128,"")) | H33: =IF($B33="","",_xlfn.XLOOKUP($B33,Catalog!$A$6:$A$128,Catalog!$H$6:$H$128,"")) | I33: =IF(OR($F33="",G33=""),"",$F33*G33) | J33: =IF(OR($F33="",H33=""),"",$F33*H33) | K33: =IF(OR(I33="",J33=""),"",J33-I33)
A34: =IF(B34="","",ROW()-6) | B34: =IFERROR(INDEX(_xlfn._xlws.FILTER(Catalog!$A$6:$A$128,(Catalog!$K$6:$K$128="GENERATE ORDER")+(Catalog!$K$6:$K$128="Yes")),ROW()-6),"") | C34: =IF($B34="","",_xlfn.XLOOKUP($B34,Catalog!$A$6:$A$128,Catalog!$C$6:$C$128,"")) | D34: =IF($B34="","",_xlfn.XLOOKUP($B34,Catalog!$A$6:$A$128,Catalog!$D$6:$D$128,"")) | E34: =IF($B34="","",_xlfn.XLOOKUP($B34,Catalog!$A$6:$A$128,Catalog!$F$6:$F$128,"")) | G34: =IF($B34="","",_xlfn.XLOOKUP($B34,Catalog!$A$6:$A$128,Catalog!$G$6:$G$128,"")) | H34: =IF($B34="","",_xlfn.XLOOKUP($B34,Catalog!$A$6:$A$128,Catalog!$H$6:$H$128,"")) | I34: =IF(OR($F34="",G34=""),"",$F34*G34) | J34: =IF(OR($F34="",H34=""),"",$F34*H34) | K34: =IF(OR(I34="",J34=""),"",J34-I34)
A35: =IF(B35="","",ROW()-6) | B35: =IFERROR(INDEX(_xlfn._xlws.FILTER(Catalog!$A$6:$A$128,(Catalog!$K$6:$K$128="GENERATE ORDER")+(Catalog!$K$6:$K$128="Yes")),ROW()-6),"") | C35: =IF($B35="","",_xlfn.XLOOKUP($B35,Catalog!$A$6:$A$128,Catalog!$C$6:$C$128,"")) | D35: =IF($B35="","",_xlfn.XLOOKUP($B35,Catalog!$A$6:$A$128,Catalog!$D$6:$D$128,"")) | E35: =IF($B35="","",_xlfn.XLOOKUP($B35,Catalog!$A$6:$A$128,Catalog!$F$6:$F$128,"")) | G35: =IF($B35="","",_xlfn.XLOOKUP($B35,Catalog!$A$6:$A$128,Catalog!$G$6:$G$128,"")) | H35: =IF($B35="","",_xlfn.XLOOKUP($B35,Catalog!$A$6:$A$128,Catalog!$H$6:$H$128,"")) | I35: =IF(OR($F35="",G35=""),"",$F35*G35) | J35: =IF(OR($F35="",H35=""),"",$F35*H35) | K35: =IF(OR(I35="",J35=""),"",J35-I35)
A36: =IF(B36="","",ROW()-6) | B36: =IFERROR(INDEX(_xlfn._xlws.FILTER(Catalog!$A$6:$A$128,(Catalog!$K$6:$K$128="GENERATE ORDER")+(Catalog!$K$6:$K$128="Yes")),ROW()-6),"") | C36: =IF($B36="","",_xlfn.XLOOKUP($B36,Catalog!$A$6:$A$128,Catalog!$C$6:$C$128,"")) | D36: =IF($B36="","",_xlfn.XLOOKUP($B36,Catalog!$A$6:$A$128,Catalog!$D$6:$D$128,"")) | E36: =IF($B36="","",_xlfn.XLOOKUP($B36,Catalog!$A$6:$A$128,Catalog!$F$6:$F$128,"")) | G36: =IF($B36="","",_xlfn.XLOOKUP($B36,Catalog!$A$6:$A$128,Catalog!$G$6:$G$128,"")) | H36: =IF($B36="","",_xlfn.XLOOKUP($B36,Catalog!$A$6:$A$128,Catalog!$H$6:$H$128,"")) | I36: =IF(OR($F36="",G36=""),"",$F36*G36) | J36: =IF(OR($F36="",H36=""),"",$F36*H36) | K36: =IF(OR(I36="",J36=""),"",J36-I36)

Sheet Summary
A1: L&M MEDICAL SOLUTIONS
A2: Inventory Summary
A3: Quick view of the merged orthopedic catalog with inventory values based on sale prices.
A5: Metric | B5: Value
A6: Total SKUs | B6: =COUNTA(Catalog!$A$5:$A$127) -> 123
A7: Total Units in Stock | B7: =SUM(Catalog!$F$5:$F$127) -> 3508
A8: Total Cost Value | B8: =SUM(Catalog!$I$5:$I$127) -> #VALUE!
A9: Total Sale Value | B9: =SUM(Catalog!$J$5:$J$127) -> #VALUE!
A12: Category | B12: Units | C12: Cost Value | D12: Sale Value
A13: Cancellous Screws | B13: =SUMIF(Catalog!$B$5:$B$127,A12,Catalog!$F$5:$F$127) -> 0 | C13: =SUMIF(Catalog!$B$5:$B$127,A12,Catalog!$I$5:$I$127) -> 0 | D13: =SUMIF(Catalog!$B$5:$B$127,A12,Catalog!$J$5:$J$127) -> 0
A14: Cannulated Screws | B14: =SUMIF(Catalog!$B$5:$B$127,A13,Catalog!$F$5:$F$127) -> 160 | C14: =SUMIF(Catalog!$B$5:$B$127,A13,Catalog!$I$5:$I$127) -> 1190000 | D14: =SUMIF(Catalog!$B$5:$B$127,A13,Catalog!$J$5:$J$127) -> 5000000
A15: External Fixator | B15: =SUMIF(Catalog!$B$5:$B$127,A14,Catalog!$F$5:$F$127) -> 180 | C15: =SUMIF(Catalog!$B$5:$B$127,A14,Catalog!$I$5:$I$127) -> 3050000 | D15: =SUMIF(Catalog!$B$5:$B$127,A14,Catalog!$J$5:$J$127) -> 7850000
A16: Gamma System | B16: =SUMIF(Catalog!$B$5:$B$127,A15,Catalog!$F$5:$F$127) -> 65 | C16: =SUMIF(Catalog!$B$5:$B$127,A15,Catalog!$I$5:$I$127) -> 3300000 | D16: =SUMIF(Catalog!$B$5:$B$127,A15,Catalog!$J$5:$J$127) -> 14950000
A17: Locked Plates | B17: =SUMIF(Catalog!$B$5:$B$127,A16,Catalog!$F$5:$F$127) -> 181 | C17: =SUMIF(Catalog!$B$5:$B$127,A16,Catalog!$I$5:$I$127) -> 203300 | D17: =SUMIF(Catalog!$B$5:$B$127,A16,Catalog!$J$5:$J$127) -> 510680
A18: Locked Screws | B18: =SUMIF(Catalog!$B$5:$B$127,A17,Catalog!$F$5:$F$127) -> 72 | C18: =SUMIF(Catalog!$B$5:$B$127,A17,Catalog!$I$5:$I$127) -> 1085 | D18: =SUMIF(Catalog!$B$5:$B$127,A17,Catalog!$J$5:$J$127) -> 5690
A19: Nails | B19: =SUMIF(Catalog!$B$5:$B$127,A18,Catalog!$F$5:$F$127) -> 130 | C19: =SUMIF(Catalog!$B$5:$B$127,A18,Catalog!$I$5:$I$127) -> 45 | D19: =SUMIF(Catalog!$B$5:$B$127,A18,Catalog!$J$5:$J$127) -> 270
A20: Plates | B20: =SUMIF(Catalog!$B$5:$B$127,A19,Catalog!$F$5:$F$127) -> 450 | C20: =SUMIF(Catalog!$B$5:$B$127,A19,Catalog!$I$5:$I$127) -> 6120000 | D20: =SUMIF(Catalog!$B$5:$B$127,A19,Catalog!$J$5:$J$127) -> 20800000
A21: Schanz Screws | B21: =SUMIF(Catalog!$B$5:$B$127,A20,Catalog!$F$5:$F$127) -> 170 | C21: =SUMIF(Catalog!$B$5:$B$127,A20,Catalog!$I$5:$I$127) -> 4320000 | D21: =SUMIF(Catalog!$B$5:$B$127,A20,Catalog!$J$5:$J$127) -> 14800000
A22: Screws | B22: =SUMIF(Catalog!$B$5:$B$127,A21,Catalog!$F$5:$F$127) -> 200 | C22: =SUMIF(Catalog!$B$5:$B$127,A21,Catalog!$I$5:$I$127) -> 1800000 | D22: =SUMIF(Catalog!$B$5:$B$127,A21,Catalog!$J$5:$J$127) -> 7000000
A23: Systems | B23: =SUMIF(Catalog!$B$5:$B$127,A22,Catalog!$F$5:$F$127) -> 1460 | C23: =SUMIF(Catalog!$B$5:$B$127,A22,Catalog!$I$5:$I$127) -> #VALUE! | D23: =SUMIF(Catalog!$B$5:$B$127,A22,Catalog!$J$5:$J$127) -> #VALUE!
A24: Wires | B24: =SUMIF(Catalog!$B$5:$B$127,A23,Catalog!$F$5:$F$127) -> 0 | C24: =SUMIF(Catalog!$B$5:$B$127,A23,Catalog!$I$5:$I$127) -> 0 | D24: =SUMIF(Catalog!$B$5:$B$127,A23,Catalog!$J$5:$J$127) -> 0

Sheet Notes
A1: L&M MEDICAL SOLUTIONS
A2: Notes & Review Points
A4: Currency | B4: USD
A5: Source | B5: Three handwritten sheets provided in chat
A6: Review | B6: 3.5 Cortex Screw L20 & L22 were inferred because the photo was partially obscured
A7: Review | B7: 5.0 Locked Screws were kept as one mixed-length line because individual lengths were not fully legible
A8: Use | B8: Update any prices/quantities directly in Catalog; Summary and Order formulas will recalculate
